methseq/__init__.py
methseq/client.py
methseq/cromwell.py
methseq/fastq.py
methseq/references.py
methseq/workflows.py
methseq/scripts/__init__.py
methseq/scripts/methseq.py
methseq/workflows/emseq-batch.wdl
methseq/workflows/emseq.wdl
methseq/workflows/pico-batch.wdl
methseq/workflows/pico.wdl
methseq/workflows/wgbs-batch.wdl
methseq/workflows/wgbs.wdl
methseq-1.0.1.dist-info/LICENSE
methseq-1.0.1.dist-info/METADATA
methseq-1.0.1.dist-info/WHEEL
methseq-1.0.1.dist-info/entry_points.txt
methseq-1.0.1.dist-info/top_level.txt
methseq-1.0.1.dist-info/RECORD
