Metadata-Version: 2.1
Name: methseq
Version: 1.0.1
Summary: Automation tool for high-throughput sequencing DNA methylation data
Home-page: https://github.com/labbcb/methseq
Author: Welliton de Souza, Danielle Brunno, Jaqueline Geraldis
Author-email: well309@gmail.com
License: GPLv3
Platform: UNKNOWN
Requires: click
Requires: requests
